_pgtestkit/__init__.py
_pgtestkit/_version.py
pgtestkit/__init__.py
pgtestkit/__main__.py
pgtestkit/py.typed
pgtestkit-0.0.1.dist-info/LICENSE
pgtestkit-0.0.1.dist-info/METADATA
pgtestkit-0.0.1.dist-info/WHEEL
pgtestkit-0.0.1.dist-info/entry_points.txt
pgtestkit-0.0.1.dist-info/top_level.txt
pgtestkit-0.0.1.dist-info/RECORD
