Metadata-Version: 2.1
Name: pgtestkit
Version: 0.0.1
Summary: A PostgreSQL testing framework for Python.
Author-email: Daniel Marín <dani4marin@gmail.com>
License: The MIT License (MIT)
Keywords: PostgreSQL,testing,framework,Python
Classifier: Programming Language :: Python :: 3
Classifier: License :: OSI Approved :: MIT License
Classifier: Operating System :: OS Independent
Classifier: Topic :: Software Development :: Testing
Classifier: Topic :: Database
Requires-Python: >=3.7
License-File: LICENSE
Requires-Dist: psycopg2>=2.9.1
Provides-Extra: dev
Requires-Dist: black; extra == "dev"
Requires-Dist: flake8; extra == "dev"
Requires-Dist: pytest-cov; extra == "dev"
